LICENSE.txt
README.md
setup.cfg
setup.py
OU_module/OU_module.py
OU_module/__init__.py
OU_module/nv_qubit.py
OU_module.egg-info/PKG-INFO
OU_module.egg-info/SOURCES.txt
OU_module.egg-info/dependency_links.txt
OU_module.egg-info/requires.txt
OU_module.egg-info/top_level.txt