Metadata-Version: 2.1
Name: OU-module
Version: 1.3.3
Summary: Models the time evolution of a spin-1/2 system with Hamiltonian subjected to random Ornstein-Uhlenbeck noise, representing an NV center spin system in diamond
Home-page: https://github.com/hendry24/OU_module
Download-URL: https://github.com/hendry24/OU_module/archive/refs/tags/v1.0.tar.gz
Author: Hendry
Author-email: hendryadi01@gmail.com
License: GPL-3.0
Keywords: Spin-1/2 Systems,OU process
Classifier: Development Status :: 3 - Alpha
Classifier: Intended Audience :: Developers
Classifier: Topic :: Software Development :: Build Tools
Classifier: License :: OSI Approved :: GNU General Public License v3 or later (GPLv3+)
Requires-Python: >=3
License-File: LICENSE.txt
